aiden_v_dlp/cli.py
aiden_v_dlp-0.1.0.dist-info/licenses/LICENSE
aiden_v_dlp-0.1.0.dist-info/METADATA
aiden_v_dlp-0.1.0.dist-info/WHEEL
aiden_v_dlp-0.1.0.dist-info/entry_points.txt
aiden_v_dlp-0.1.0.dist-info/top_level.txt
aiden_v_dlp-0.1.0.dist-info/RECORD
