Metadata-Version: 2.4
Name: aiden-v-dlp
Version: 0.1.0
Summary: Aiden Video Downloader: a friendly wrapper around yt-dlp
Author-email: Your Name <you@example.com>
License: MIT
Requires-Python: >=3.8
License-File: LICENSE
Requires-Dist: yt-dlp>=2024.3.10
Dynamic: license-file
